npnn/__init__.py
npnn/autograd.py
npnn/base.py
npnn/functional.py
npnn/nn.py
npnn/optim.py
npnn-0.1.1.dist-info/LICENSE
npnn-0.1.1.dist-info/METADATA
npnn-0.1.1.dist-info/WHEEL
npnn-0.1.1.dist-info/top_level.txt
npnn-0.1.1.dist-info/RECORD
