Metadata-Version: 2.1
Name: npnn
Version: 0.1.1
Summary: NumPy Neural Network
Author-email: Yang Zhang <mail@yangzhang.site>
License: MIT License
Project-URL: Homepage, https://github.com/AIboy996/npnn
Keywords: numpy,neural network,machine learning,autograd
Classifier: Development Status :: 3 - Alpha
Classifier: Intended Audience :: Developers
Classifier: Programming Language :: Python :: 3.9
Classifier: Programming Language :: Python :: 3.10
Classifier: Programming Language :: Python :: 3.11
Classifier: Programming Language :: Python :: 3.12
Classifier: License :: OSI Approved :: MIT License
Classifier: Operating System :: OS Independent
Requires-Python: >=3.9
License-File: LICENSE
Requires-Dist: numpy
Provides-Extra: cuda11x
Requires-Dist: cupy-cuda11x ; extra == 'cuda11x'
Provides-Extra: cuda12x
Requires-Dist: cupy-cuda12x ; extra == 'cuda12x'
